comatrix/__init__.py
comatrix-0.0.0.dist-info/LICENSE
comatrix-0.0.0.dist-info/METADATA
comatrix-0.0.0.dist-info/WHEEL
comatrix-0.0.0.dist-info/top_level.txt
comatrix-0.0.0.dist-info/RECORD
